<?xml version="1.0" encoding="UTF-8"?>
<objects serializationModel="Studio.01.10.00">
    <object class="AudioFile" id="{3e54dd21-f1e7-471a-897e-e129b90527bd}">
        <property name="assetPath">
            <value>Nem.WAV</value>
        </property>
        <property name="frequencyInKHz">
            <value>44.0999985</value>
        </property>
        <property name="channelCount">
            <value>2</value>
        </property>
        <property name="length">
            <value>1.5920181405895693</value>
        </property>
        <relationship name="masterAssetFolder">
            <destination>{f38dd8eb-579e-4a3d-8c38-10be1402fa2b}</destination>
        </relationship>
    </object>
</objects>
